{"i8TRmyjscXMDqRaATLqr1w==":"ds-cutout-sm.png","AChsi20OQuv72FnGgfqieA==":"1.png","JVyRUFh/uF2Bv4pm0Ad5pw==":"ds-banner1.jpg","gKw1K+MBZsSC3or1kq2oJA==":"16997908-10154359642803671-2573802345365204561-n.jpg","mxUFhBxApj704LtVrCo9pg==":"ds-43.jpg","JuA9xwNv2QSHq5CwEEoH2g==":"mbr.jpg","wSEYl2/xbAZI1Eqo6deoZQ==":"mbr-1.jpg","AHxmUI+Hk+hv0gtddHeWpA==":"mbr-2.jpg","a4xfrDB6fKbWgujq1J6jdA==":"mbr-3.jpg","tmLObDXxcGh5OOOyCPCOpg==":"mbr-4.jpg","p1jPmHqd9wRA/w/v1E1GWw==":"mbr-5.jpg","jziKxmB03HoPdHkDN1QmoQ==":"mbr-6.jpg","3raJ+wbxSCGcDS6XQoRUKw==":"mbr-7.jpg","KxR7TMbZVD4niChfUKVBLw==":"mbr-8.jpg","BOq+vjo1JTrGkv6MKh7BBA==":"mbr.png","YISjzNnw9FwhWJWCOqywug==":"mbr-1.png","vMiXMP2kkv2kjRjrZtbjKQ==":"whatsapp-image-2023-02-16-at-10.48.33.jpeg","D8WtMHRwJs0caBGmDJ5Skw==":"whatsapp-image-2023-02-16-at-10.48.35.jpeg","SO7bx4IdoCes/7MRiF5YeA==":"wiring1.jpeg","lbtaFSWObVtaxSnO9u6ihA==":"circuit-box.jpeg","3H6Vf72kP5jES3m6s76O5Q==":"wiring2.jpeg","RYCDNnKrGyXvGfB+Ke4/ig==":"speaker1.jpeg","kZORV6TSh4GD/PWV6RoRDA==":"pa-mic.jpeg","JslE5ttCaLRU/Cx89xkhWA==":"nurse-call.jpeg","4eJ7C7yGgjLsKQICj366oA==":"cctvcamera.jpeg","Coqje0s9vM8oNcHcQMetrA==":"cabling1.jpeg","dLJeRUXLNOyal/5tNkutGg==":"cabling.jpeg","gJV3eZor+D7ogHQExgt/vg==":"cctv-monitors.jpeg","9VA9IiN+IJwQWYNbiG2LDA==":"eticket.jpeg","HnKfHFoGJ9TsFbwqn+ic3g==":"boom-barrier.jpeg"}